requirementsGet/__init__.py
requirementsget-1.0.6.dist-info/licenses/LICENSE
requirementsget-1.0.6.dist-info/METADATA
requirementsget-1.0.6.dist-info/WHEEL
requirementsget-1.0.6.dist-info/top_level.txt
requirementsget-1.0.6.dist-info/RECORD
